yaxai/__init__.py
yaxai/cli.py
yaxai/ghurl.py
yaxai/yax.py
yaxai-0.15.0.dist-info/METADATA
yaxai-0.15.0.dist-info/WHEEL
yaxai-0.15.0.dist-info/entry_points.txt
yaxai-0.15.0.dist-info/licenses/LICENSE
yaxai-0.15.0.dist-info/RECORD
