Metadata-Version: 2.4
Name: yaxai
Version: 0.15.0
Summary: 
License-File: LICENSE
Author: Henryk Konsek
Author-email: hekonsek@gmail.com
Requires-Python: >=3.12
Classifier: Programming Language :: Python :: 3
Classifier: Programming Language :: Python :: 3.12
Classifier: Programming Language :: Python :: 3.13
Classifier: Programming Language :: Python :: 3.14
Requires-Dist: pydantic (>=2.12.2,<3.0.0)
Requires-Dist: pyyaml (>=6.0)
Requires-Dist: typer (>=0.12.3)
